multivalue/BaseDialect.py
multivalue/Dialects.py
multivalue/__init__.py
multivalue/build_attestation_vectors.py
multivalue/build_benefactive_ditransitive_verb_list.py
multivalue/build_coqa_value.py
multivalue/build_hit_csv.py
multivalue/build_value.py
multivalue/inflect/__init__.py
multivalue/inflect/base.py
multivalue/inflect/english.py
multivalue/resources/adv_adj_degree_modifier.json
multivalue/resources/adv_adj_flat.json
multivalue/resources/attestation_vectors.csv
multivalue/resources/benefactive_verbs.txt
multivalue/resources/concreteness.csv
multivalue/resources/det_plural.json
multivalue/resources/det_possessive_obj.json
multivalue/resources/ditransitive_dobj_verbs.txt
multivalue/resources/ewave.csv
multivalue/resources/feature_id_to_function_name.json
multivalue/resources/mass_nouns.txt
multivalue/resources/modals_past.json
multivalue/resources/negatives.json
multivalue/resources/negatives_no_more.json
multivalue/resources/noun_concreteness.json
multivalue/resources/people_terms.csv
multivalue/resources/possessives.json
multivalue/resources/pron_obj_to_subj.json
multivalue/resources/reflexives_aave.json
multivalue/resources/reflexives_emphatic.json
multivalue/resources/reflexives_number_swap.json
multivalue/resources/reflexives_obj_pron.json
multivalue/resources/reflexives_regularized.json
multivalue/resources/reflexives_subj.json
multivalue/resources/transitive_dobj_verbs.txt
multivalue/resources/unittests.json
multivalue/resources/varieties.csv
multivalue/resources/verb_transitivity.tsv
value_nlp-0.3.dist-info/METADATA
value_nlp-0.3.dist-info/WHEEL
value_nlp-0.3.dist-info/licenses/LICENSE
value_nlp-0.3.dist-info/RECORD
