Metadata-Version: 2.3
Name: value-nlp
Version: 0.3
Summary: A Framework for Cross-Dialectal NLP
Project-URL: Homepage, https://value-nlp.org
Project-URL: Bug Tracker, https://github.com/SALT-NLP/multi-value/issues
Author-email: Will Held <wheld3@gatech.edu>, Caleb Ziems <cjziems@stanford.edu>
License-File: LICENSE
Classifier: Development Status :: 4 - Beta
Classifier: Intended Audience :: Science/Research
Classifier: License :: OSI Approved :: Apache Software License
Classifier: Operating System :: MacOS :: MacOS X
Classifier: Operating System :: POSIX :: Linux
Classifier: Programming Language :: Python :: 3
Requires-Python: >=3.10
Requires-Dist: geopy==2.2.0
Requires-Dist: inflect==5.5.2
Requires-Dist: lemminflect==0.2.2
Requires-Dist: nltk==3.5
Requires-Dist: numpy
Requires-Dist: pandas
Requires-Dist: peft
Requires-Dist: spacy==3.7.4
Requires-Dist: stanza==1.8.2
Requires-Dist: tqdm
Requires-Dist: transformers
